{"cameraMode":{"drawMode":0,"name":"Shaded","section":"Shading Mode"},"sceneLighting":true,"audioPlay":false,"sceneViewState":{"m_AlwaysRefresh":false,"showFog":true,"showSkybox":true,"showFlares":true,"showImageEffects":true,"showParticleSystems":true,"showVisualEffectGraphs":true,"m_FxEnabled":true},"in2DMode":false,"pivot":{"x":-5.358307361602783,"y":0.4136089086532593,"z":34.08311462402344},"rotation":{"x":0.507909893989563,"y":0.1028669998049736,"z":-0.061241235584020618,"w":0.8531132340431213},"size":11.852887153625489,"orthographic":false}